aiousps/__init__.py
aiousps/address.py
aiousps/constants.py
aiousps/helpers.py
aiousps/usps.py
tests/__init__.py
tests/constants.py
tests/test_address.py
tests/test_api.py
tests/test_helpers.py
aiousps-0.1.3.dist-info/LICENSE
aiousps-0.1.3.dist-info/METADATA
aiousps-0.1.3.dist-info/WHEEL
aiousps-0.1.3.dist-info/top_level.txt
aiousps-0.1.3.dist-info/RECORD
