Metadata-Version: 2.1
Name: aiousps
Version: 0.1.3
Summary: Python wrapper for the USPS API
Home-page: http://github.com/lengau/usps-api
Author: Alex Lowe
Author-email: amlowe@lengau.net
License: MIT
Keywords: usps shipping
Platform: UNKNOWN
Classifier: Development Status :: 3 - Alpha
Classifier: Intended Audience :: Information Technology
Classifier: License :: OSI Approved :: MIT License
Classifier: Natural Language :: English
Classifier: Programming Language :: Python
Classifier: Programming Language :: Python :: 3
Classifier: Programming Language :: Python :: 3.6
Classifier: Programming Language :: Python :: 3.7
Classifier: Programming Language :: Python :: 3.8
Classifier: Programming Language :: Python :: 3.9
Classifier: Topic :: Software Development :: Libraries :: Python Modules
Classifier: Topic :: Software Development :: Testing
Classifier: Topic :: Utilities
Requires-Dist: requests
Requires-Dist: lxml
Requires-Dist: xmltodict
Requires-Dist: dataclasses ; python_version == "3.6"
